repertoire/__init__.py
repertoire/latex.py
repertoire/repertoire.py
repertoire/scheduler.py
repertoire/term.py
repertoire/binders/__init__.py
repertoire/binders/binder.py
repertoire/binders/math.py
repertoire/binders/people.py
repertoire/binders/quotes.py
repertoire/sheets/__init__.py
repertoire/sheets/math.py
repertoire/sheets/person.py
repertoire/sheets/quote.py
repertoire/sheets/sheet.py
repertoire-0.0.2.dist-info/LICENSE
repertoire-0.0.2.dist-info/METADATA
repertoire-0.0.2.dist-info/WHEEL
repertoire-0.0.2.dist-info/entry_points.txt
repertoire-0.0.2.dist-info/top_level.txt
repertoire-0.0.2.dist-info/RECORD
