Metadata-Version: 2.1
Name: repertoire
Version: 0.0.2
Summary: Spaced repetition in plain text
Home-page: https://github.com/agajews/repertoire
Author: Alex Gajewski
Author-email: agajews@gmail.com
License: UNKNOWN
Platform: UNKNOWN
Classifier: Programming Language :: Python :: 3
Classifier: License :: OSI Approved :: MIT License
Classifier: Operating System :: OS Independent
Requires-Dist: blessings
Requires-Dist: click
Requires-Dist: getkey
